cedict/__init__.py
cedict/cedict.py
cedict/csv/EnWords.csv
cedict/db/words.db
cedict-0.1.0.dist-info/LICENSE
cedict-0.1.0.dist-info/METADATA
cedict-0.1.0.dist-info/WHEEL
cedict-0.1.0.dist-info/top_level.txt
cedict-0.1.0.dist-info/RECORD
