Metadata-Version: 2.1
Name: cedict
Version: 0.1.0
Summary: A Chinese English dictionary.
Author: Peter
Author-email: Peter <findpeter@163.com>
Project-URL: Homepage, https://github.com/peterszns/cedict
Project-URL: Bug Tracker, https://github.com/peterszns/cedict/issues
Classifier: Programming Language :: Python :: 3
Classifier: License :: OSI Approved :: MIT License
Classifier: Operating System :: OS Independent
Requires-Python: >=3.7
License-File: LICENSE
